odoo/addons/account_invoice_base_invoicing_mode/README.rst
odoo/addons/account_invoice_base_invoicing_mode/__init__.py
odoo/addons/account_invoice_base_invoicing_mode/__manifest__.py
odoo/addons/account_invoice_base_invoicing_mode/data/queue_job_data.xml
odoo/addons/account_invoice_base_invoicing_mode/i18n/account_invoice_base_invoicing_mode.pot
odoo/addons/account_invoice_base_invoicing_mode/i18n/es.po
odoo/addons/account_invoice_base_invoicing_mode/i18n/fr.po
odoo/addons/account_invoice_base_invoicing_mode/models/__init__.py
odoo/addons/account_invoice_base_invoicing_mode/models/account_invoice.py
odoo/addons/account_invoice_base_invoicing_mode/models/queue_job.py
odoo/addons/account_invoice_base_invoicing_mode/models/res_partner.py
odoo/addons/account_invoice_base_invoicing_mode/models/sale_order.py
odoo/addons/account_invoice_base_invoicing_mode/readme/CONTRIBUTORS.rst
odoo/addons/account_invoice_base_invoicing_mode/readme/CREDITS.rst
odoo/addons/account_invoice_base_invoicing_mode/readme/DESCRIPTION.rst
odoo/addons/account_invoice_base_invoicing_mode/readme/ROADMAP.rst
odoo/addons/account_invoice_base_invoicing_mode/static/description/icon.png
odoo/addons/account_invoice_base_invoicing_mode/static/description/index.html
odoo/addons/account_invoice_base_invoicing_mode/tests/__init__.py
odoo/addons/account_invoice_base_invoicing_mode/tests/common.py
odoo/addons/account_invoice_base_invoicing_mode/tests/test_invoice_base_mode.py
odoo/addons/account_invoice_base_invoicing_mode/views/res_partner.xml
odoo14_addon_account_invoice_base_invoicing_mode-14.0.1.2.2.dist-info/METADATA
odoo14_addon_account_invoice_base_invoicing_mode-14.0.1.2.2.dist-info/WHEEL
odoo14_addon_account_invoice_base_invoicing_mode-14.0.1.2.2.dist-info/top_level.txt
odoo14_addon_account_invoice_base_invoicing_mode-14.0.1.2.2.dist-info/RECORD
